{
  "eventos": [
    {
      "id": 1,
      "evento": "Feijoada Beneficente",
      "data": "2023-06-06",
      "hora_inicio": "11:00",
      "hora_fim": "15:00",
      "detalhe": "Feijoada beneficente para ajudar a casa de apoio da Graça",
      "imagem": "http://localhost:3000/9b1deb4d-3b7d-4bad-9bdd-2b0d7b3dcb55.png"
    },
    {
      "id": 2,
      "evento": "Doação",
      "data": "2023-06-06",
      "hora_inicio": "11:00",
      "hora_fim": "15:00",
      "detalhe": "Doação de roupas",
      "imagem": "http://localhost:3000/9b1deb4d-3b7d-4bad-9bdd-2b0d7b3dcb55.png"
    },
    {
      "id": 3,
      "evento": "Vaquinha da Ju",
      "data": "2023-06-06",
      "hora_inicio": "00:01",
      "hora_fim": "23:00",
      "detalhe": "Doação de dinheiro.",
      "imagem": "http://localhost:3000/9b1deb4d-3b7d-4bad-9bdd-2b0d7b3dcb55.png"
    },
    {
      "evento": "A",
      "data": "1",
      "hora_inicio": "1",
      "hora_fim": "1",
      "detalhe": "A",
      "imagem": "",
      "id": 4
    },
    {
      "evento": "B",
      "data": "2",
      "hora_inicio": "2",
      "hora_fim": "2",
      "detalhe": "B",
      "imagem": "",
      "id": 5
    }
  ]
}